<?xml version="1.0" encoding="utf-8"?><DEFECTS><DEFECT>
    <SFA>
      <FILEPATH>C:\Users\Euler\Desktop\Meu Raytracer\Raytracer\</FILEPATH>
      <FILENAME>Canvas.h</FILENAME>
      <LINE>59</LINE>
      <COLUMN>10</COLUMN>
    </SFA>
    <DEFECTCODE>6993</DEFECTCODE>
    <DESCRIPTION>A análise de código ignora construções OpenMP; analisando código de um único thread.</DESCRIPTION>
    <FUNCTION></FUNCTION>
    <DECORATED></DECORATED>
    <FUNCLINE>0</FUNCLINE>
    <PATH></PATH>
  </DEFECT></DEFECTS>